setup.py
bk/__init__.py
bk/bk
bk.egg-info/PKG-INFO
bk.egg-info/SOURCES.txt
bk.egg-info/dependency_links.txt
bk.egg-info/requires.txt
bk.egg-info/top_level.txt