Metadata-Version: 1.1
Name: bk
Version: 0.1.4
Summary: An utility that lets you change desktop background for GNU/Linux and Windows.
Home-page: https://github.com/rr-/bk
Author: rr-
Author-email: rr-@sakuya.pl
License: UNKNOWN
Download-URL: https://github.com/rr-/bk/tarball/0.1.4
Keywords: wallpaper,screen,monitor,desktop
Platform: UNKNOWN
